setup.py
mrrdt_vision/__init__.py
mrrdt_vision.egg-info/PKG-INFO
mrrdt_vision.egg-info/SOURCES.txt
mrrdt_vision.egg-info/dependency_links.txt
mrrdt_vision.egg-info/requires.txt
mrrdt_vision.egg-info/top_level.txt
mrrdt_vision/obj_detect/__init__.py
mrrdt_vision/obj_detect/display.py
mrrdt_vision/obj_detect/roomba_cnn.py
mrrdt_vision/obj_detect/object_detection/__init__.py
mrrdt_vision/obj_detect/object_detection/eval.py
mrrdt_vision/obj_detect/object_detection/eval_util.py
mrrdt_vision/obj_detect/object_detection/evaluator.py
mrrdt_vision/obj_detect/object_detection/export_inference_graph.py
mrrdt_vision/obj_detect/object_detection/exporter.py
mrrdt_vision/obj_detect/object_detection/exporter_test.py
mrrdt_vision/obj_detect/object_detection/train.py
mrrdt_vision/obj_detect/object_detection/trainer.py
mrrdt_vision/obj_detect/object_detection/trainer_test.py
mrrdt_vision/obj_detect/object_detection/anchor_generators/__init__.py
mrrdt_vision/obj_detect/object_detection/anchor_generators/grid_anchor_generator.py
mrrdt_vision/obj_detect/object_detection/anchor_generators/grid_anchor_generator_test.py
mrrdt_vision/obj_detect/object_detection/anchor_generators/multiple_grid_anchor_generator.py
mrrdt_vision/obj_detect/object_detection/anchor_generators/multiple_grid_anchor_generator_test.py
mrrdt_vision/obj_detect/object_detection/box_coders/__init__.py
mrrdt_vision/obj_detect/object_detection/box_coders/faster_rcnn_box_coder.py
mrrdt_vision/obj_detect/object_detection/box_coders/faster_rcnn_box_coder_test.py
mrrdt_vision/obj_detect/object_detection/box_coders/keypoint_box_coder.py
mrrdt_vision/obj_detect/object_detection/box_coders/keypoint_box_coder_test.py
mrrdt_vision/obj_detect/object_detection/box_coders/mean_stddev_box_coder.py
mrrdt_vision/obj_detect/object_detection/box_coders/mean_stddev_box_coder_test.py
mrrdt_vision/obj_detect/object_detection/box_coders/square_box_coder.py
mrrdt_vision/obj_detect/object_detection/box_coders/square_box_coder_test.py
mrrdt_vision/obj_detect/object_detection/builders/__init__.py
mrrdt_vision/obj_detect/object_detection/builders/anchor_generator_builder.py
