Metadata-Version: 1.0
Name: mrrdt-vision
Version: 1.1.3
Summary: mrrdt_vision 1.1.3
Home-page: https://github.com/MST-MRR/IARC-2018
Author: Christopher O'Toole
Author-email: cdocq9@mst.edu
License: MIT
Platform: UNKNOWN
